django_herobiz_ds/.DS_Store
django_herobiz_ds/__init__.py
django_herobiz_ds/admin.py
django_herobiz_ds/apps.py
django_herobiz_ds/forms.py
django_herobiz_ds/models.py
django_herobiz_ds/sitemaps.py
django_herobiz_ds/tests.py
django_herobiz_ds/urls.py
django_herobiz_ds/views.py
django_herobiz_ds/migrations/0001_initial.py
django_herobiz_ds/migrations/0002_portfolio_client.py
django_herobiz_ds/migrations/0003_post_profile.py
django_herobiz_ds/migrations/0004_remove_portfolio_filter_remove_post_author_and_more.py
django_herobiz_ds/migrations/__init__.py
django_herobiz_ds/static/herobizds/css/main.css
django_herobiz_ds/static/herobizds/css/variables-blue.css
django_herobiz_ds/static/herobizds/css/variables-green.css
django_herobiz_ds/static/herobizds/css/variables-orange.css
django_herobiz_ds/static/herobizds/css/variables-pink.css
django_herobiz_ds/static/herobizds/css/variables-purple.css
django_herobiz_ds/static/herobizds/css/variables-red.css
django_herobiz_ds/static/herobizds/css/variables.css
django_herobiz_ds/static/herobizds/img/about-bg.png
django_herobiz_ds/static/herobizds/img/faq.jpg
django_herobiz_ds/static/herobizds/img/hero-bg.png
django_herobiz_ds/static/herobizds/img/onfocus-content-bg.jpg
django_herobiz_ds/static/herobizds/img/pricing-bg.jpg
django_herobiz_ds/static/herobizds/js/main.js
django_herobiz_ds/static/herobizds/scss/_blog.scss
django_herobiz_ds/static/herobizds/scss/_footer.scss
django_herobiz_ds/static/herobizds/scss/_general.scss
django_herobiz_ds/static/herobizds/scss/_header.scss
django_herobiz_ds/static/herobizds/scss/_index.scss
django_herobiz_ds/static/herobizds/scss/_nav.scss
django_herobiz_ds/static/herobizds/scss/_portfolio-details.scss
django_herobiz_ds/static/herobizds/scss/main.scss
django_herobiz_ds/static/herobizds/scss/variables-blue.css
django_herobiz_ds/static/herobizds/scss/variables-green.css
django_herobiz_ds/static/herobizds/scss/variables-orange.css
django_herobiz_ds/static/herobizds/scss/variables-pink.css
django_herobiz_ds-4.2.0.dist-info/LICENSE
django_herobiz_ds-4.2.0.dist-info/WHEEL
django_herobiz_ds-4.2.0.dist-info/METADATA
django_herobiz_ds-4.2.0.dist-info/RECORD
