Metadata-Version: 2.1
Name: django_herobiz_ds
Version: 4.2.0
Summary: my demiansoft templates
Author-email: Hyungjin Kim <hj3415@gmail.com>
Classifier: License :: OSI Approved :: MIT License
Requires-Dist: Django >= 4.2.11
Requires-Dist: libsass>=0.23.0
Requires-Dist: django-analyticsds >= 0.3.1
Requires-Dist: django-calendards >= 0.4.0
Requires-Dist: django-modalds >= 0.1.0
Requires-Dist: django-utilsds >= 0.7.0
Requires-Dist: django-postds >= 1.4.0
Requires-Dist: django-markdownify >= 0.9.3
Project-URL: Home, https://www.demiansoft.com
